resultsdb_api.py
resultsdb_api-2.1.5.dist-info/LICENSE
resultsdb_api-2.1.5.dist-info/METADATA
resultsdb_api-2.1.5.dist-info/WHEEL
resultsdb_api-2.1.5.dist-info/top_level.txt
resultsdb_api-2.1.5.dist-info/RECORD
